airflow_hop/__init__.py
airflow_hop/hooks.py
airflow_hop/operators.py
airflow_hop/plugin.py
airflow_hop/xml.py
airflow_hop_plugin-0.1.0b7.dist-info/LICENSE
airflow_hop_plugin-0.1.0b7.dist-info/METADATA
airflow_hop_plugin-0.1.0b7.dist-info/WHEEL
airflow_hop_plugin-0.1.0b7.dist-info/entry_points.txt
airflow_hop_plugin-0.1.0b7.dist-info/top_level.txt
airflow_hop_plugin-0.1.0b7.dist-info/RECORD
