Metadata-Version: 2.1
Name: airflow-hop-plugin
Version: 0.1.0b7
Home-page: https://github.com/damavis/airflow-hop-plugin
Author: Damavis
Author-email: info@damavis.com
License: Apache 2.0
Classifier: Environment :: Plugins
Classifier: License :: OSI Approved :: Apache Software License
Classifier: Operating System :: Unix
Classifier: Operating System :: MacOS
Classifier: Operating System :: Microsoft :: Windows
Classifier: Programming Language :: Python :: 3.6
Classifier: Programming Language :: Python :: 3.7
Classifier: Programming Language :: Python :: 3.8
Classifier: Programming Language :: Python :: 3.9
Requires-Python: >=3
License-File: LICENSE
Requires-Dist: xmltodict >=0.12.0
